{"cameraMode":{"drawMode":0,"name":"Shaded","section":"Shading Mode"},"sceneLighting":true,"audioPlay":false,"sceneViewState":{"m_AlwaysRefresh":false,"showFog":true,"showSkybox":true,"showFlares":true,"showImageEffects":true,"showParticleSystems":true,"showVisualEffectGraphs":true,"m_FxEnabled":true},"in2DMode":false,"pivot":{"x":0.8629012107849121,"y":6.037349700927734,"z":-1.1576285362243653},"rotation":{"x":-0.37909039855003359,"y":0.0047113364562392239,"z":-0.0019467537058517337,"w":-0.9253665804862976},"size":14.938888549804688,"orthographic":false}